setup.cfg
setup.py
FetchNovels.egg-info/PKG-INFO
FetchNovels.egg-info/SOURCES.txt
FetchNovels.egg-info/dependency_links.txt
FetchNovels.egg-info/entry_points.txt
FetchNovels.egg-info/top_level.txt
novel/__init__.py
novel/base.py
novel/cli.py
novel/config.py
novel/db.py
novel/decorators.py
novel/factory.py
novel/main.py
novel/models.py
novel/serial.py
novel/single.py
novel/utils.py
novel/sources/__init__.py
novel/sources/aastory.py
novel/sources/akxs6.py
novel/sources/amxs520.py
novel/sources/avcool.py
novel/sources/baishulou.py
novel/sources/bbs1766.py
novel/sources/benbenwx.py
novel/sources/bgif2.py
novel/sources/biquge.py
novel/sources/biqugex.py
novel/sources/book3k.py
novel/sources/bz11.py
novel/sources/cmshy.py
novel/sources/cool18.py
novel/sources/danmei123.py
novel/sources/doubangroup.py
novel/sources/doubangroupall.py
novel/sources/dzxsw.py
novel/sources/feizw.py
novel/sources/gigacircle.py
novel/sources/h528.py
novel/sources/haxsc.py
novel/sources/haxtxt.py
novel/sources/hhss91.py
novel/sources/hshubao.py
novel/sources/icnsp.py
novel/sources/jjwxc.py
novel/sources/klxsw.py
novel/sources/lewenxiaoshuo.py
novel/sources/lou19.py
novel/sources/lt92.py
novel/sources/lurenshu.py
novel/sources/lwxs.py
novel/sources/lwxs520.py
novel/sources/lwxsw.py
novel/sources/mianfeixiaoshuoyueduwang.py
novel/sources/myshuge.py
novel/sources/park6.py
novel/sources/piaotian.py
novel/sources/piaotiancc.py
novel/sources/ppxhh.py
novel/sources/qbxs8.py
novel/sources/qu.py
novel/sources/ranwen.py
novel/sources/sanhao3.py
novel/sources/sdragon.py
novel/sources/sexinsex.py
novel/sources/shu69.py
novel/sources/shushu8.py
novel/sources/shushuwu.py
novel/sources/sis.py
novel/sources/sto.py
novel/sources/ttshuba.py
novel/sources/ttzw.py
novel/sources/ttzw5.py
novel/sources/ucxsw.py
novel/sources/uks5.py
novel/sources/wdxs.py
novel/sources/windmoonland.py
novel/sources/wutuxs.py
novel/sources/xianwang123.py
novel/sources/xiaoqiangxs.py
novel/sources/xs365.py
novel/sources/xsg915.py
novel/sources/xueyinglingzhu5200.py
novel/sources/yawenb.py
novel/sources/yazhouse8.py
novel/sources/yfzww.py
novel/sources/yixia.py
novel/sources/ymwen.py
novel/sources/yq33.py
