Metadata-Version: 1.1
Name: FetchNovels
Version: 0.9.6.2
Summary: Fetch novels from Internet
Home-page: https://github.com/wangjiezhe/FetchNovels
Author: wangjiezhe
Author-email: wangjiezhe@gmail.com
License: GPLv3
Platform: UNKNOWN
Classifier: Development Status :: 4 - Beta
Classifier: Environment :: Console
Classifier: License :: OSI Approved :: GNU General Public License v3 (GPLv3)
Classifier: Natural Language :: English
Classifier: Programming Language :: Python :: 3
Classifier: Programming Language :: Python :: 3.4
Classifier: Programming Language :: Python :: 3.5
Classifier: Programming Language :: Python :: 3.6
